LICENSE
MANIFEST.in
README.rst
setup.py
prototurk/__init__.py
prototurk/server.py
prototurk/version.py
prototurk.egg-info/PKG-INFO
prototurk.egg-info/SOURCES.txt
prototurk.egg-info/dependency_links.txt
prototurk.egg-info/requires.txt
prototurk.egg-info/top_level.txt
prototurk/static/bootstrap-4.3.1.min.css
prototurk/static/bootstrap-4.3.1.min.js
prototurk/static/jquery-3.4.1.js
prototurk/static/popper-1.14.7.min.js
prototurk/templates/task-iframe.html
prototurk/templates/task-list.html
prototurk/templates/task.html
scripts/prototurk
scripts/prototurk-populate