Metadata-Version: 2.1
Name: prototurk
Version: 0.4.2
Summary: Simple server and script for rapidly prototyping Mechanical Turk interfaces
Home-page: https://github.com/hltcoe/prototurk
Author: Craig Harman
Author-email: craig@craigharman.net
License: BSD
Platform: UNKNOWN
Classifier: Framework :: Bottle
Classifier: Intended Audience :: Developers
Classifier: Intended Audience :: Science/Research
Classifier: License :: OSI Approved :: BSD License
Classifier: Programming Language :: Python :: 3 :: Only
License-File: LICENSE
